DataLibrary/__init__.py
DataLibrary/categorical_encoder.py
DataLibrary/data_type_converter.py
DataLibrary/date_time_handler.py
DataLibrary/featureengineer.py
DataLibrary/missing_value_handler.py
DataLibrary/outlier_handler.py
DataLibrary/scaler.py
DataLibrary/setup.py
DataLibrary/text_cleaner.py
DataLibrary-0.0.3.dist-info/METADATA
DataLibrary-0.0.3.dist-info/WHEEL
DataLibrary-0.0.3.dist-info/top_level.txt
DataLibrary-0.0.3.dist-info/RECORD
