Metadata-Version: 2.1
Name: DataLibrary
Version: 0.0.3
Requires-Python: >=3.6
Requires-Dist: pandas
Requires-Dist: scikit-learn
Requires-Dist: nltk
Requires-Dist: numpy
